[
  {
    "cTitle": "108年01月、02月統一發票中獎號碼",
    "cCode_1": "00106725",
    "cCode_2": "90819218",
    "cCode_3": [
      "13440631",
      "26650552",
      "09775722"
    ],
    "cCode_4": [
      "809",
      "264"
    ]
  },
  {
    "cTitle": "107年09月、10月統一發票中獎號碼",
    "cCode_1": "96363025",
    "cCode_2": "69095110",
    "cCode_3": [
      "96745865",
      "98829035",
      "45984442"
    ],
    "cCode_4": [
      "292",
      "650",
      "230"
    ]
  },
  {
    "cTitle": "107年07月、08月統一發票中獎號碼",
    "cCode_1": "73372972",
    "cCode_2": "22315462",
    "cCode_3": [
      "91903003",
      "16228722",
      "03270598"
    ],
    "cCode_4": [
      "163",
      "983",
      "814"
    ]
  },
  {
    "cTitle": "107年05月、06月統一發票中獎號碼",
    "cCode_1": "20048019",
    "cCode_2": "02142605",
    "cCode_3": [
      "21240109",
      "78323535",
      "18549847"
    ],
    "cCode_4": [
      "706",
      "574"
    ]
  },
  {
    "cTitle": "107年03月、04月統一發票中獎號碼",
    "cCode_1": "12342126",
    "cCode_2": "80740977",
    "cCode_3": [
      "36822639",
      "38786238",
      "87204837"
    ],
    "cCode_4": [
      "991",
      "715"
    ]
  },
  {
    "cTitle": "107年01月、02月統一發票中獎號碼",
    "cCode_1": "21735266",
    "cCode_2": "91874254",
    "cCode_3": [
      "56065209",
      "05739340",
      "69001612"
    ],
    "cCode_4": [
      "591",
      "342"
    ]
  }
]